{"name":"Maverick","stats":"1 Armor, 3 Speed","gadget_1":"Breaching Torch","gadget_2":["Claymore","Frag Grenades"],"icon":"https://i.imgur.com/rKX66ni.png","description":"Blowtorch capable of burning holes through reinforced walls at an almost inaudable level","weapons":{"primary":[{"name":"AR-15.50","damage":"62","rof":"Semi-Auto","mag_size":"10 + 1","total_ammo":"71","sights":"Red Dot, Holographic, Reflex, ACOG","barrels":"Suppressor, Flash Hider, Compensator, Muzzle Brake","grips":"Vertical Grip, Angled Grip","under_barrel":"Laser","weapon_type":"Assault Rifle","image":"https://i.ibb.co/Wx3dTYr/AR-15-50.png"},{"name":"M4","damage":"44","rof":"750 RPM","mag_size":"30 + 1","total_ammo":"181","sights":"Red Dot, Holographic, Reflex, ACOG","barrels":"Suppressor, Flash Hider, Compensator, Muzzle Brake","grips":"Vertical Grip, Angled Grip","under_barrel":"Laser","weapon_type":"Assault Rifle","image":"https://i.ibb.co/g4xty0M/M4.png"}],"secondary":[{"name":"1911 TACOPS","damage":"55","rof":"Semi-Auto","mag_size":"8 + 1","total_ammo":"41","sights":"No sights available","barrels":"Suppressor, Muzzle Brake","grips":"No grips available","under_barrel":"Laser","weapon_type":"Handgun","image":"https://i.ibb.co/XpWXd29/1911-TACOPS.png"}]}}